optimum/habana/__init__.py
optimum/habana/checkpoint_utils.py
optimum/habana/version.py
optimum/habana/AutoAWQ/gemm_hpu.py
optimum/habana/accelerate/__init__.py
optimum/habana/accelerate/accelerator.py
optimum/habana/accelerate/state.py
optimum/habana/accelerate/utils/__init__.py
optimum/habana/accelerate/utils/dataclasses.py
optimum/habana/accelerate/utils/other.py
optimum/habana/accelerate/utils/transformer_engine.py
optimum/habana/diffusers/__init__.py
optimum/habana/diffusers/models/__init__.py
optimum/habana/diffusers/models/attention_processor.py
optimum/habana/diffusers/models/controlnet_sdv.py
optimum/habana/diffusers/models/embeddings.py
optimum/habana/diffusers/models/unet_2d.py
optimum/habana/diffusers/models/unet_2d_condition.py
optimum/habana/diffusers/models/unet_spatio_temporal_condition_controlnet.py
optimum/habana/diffusers/models/autoencoders/autoencoder_kl_cogvideox.py
optimum/habana/diffusers/models/transformers/cogvideox_transformer_3d.py
optimum/habana/diffusers/pipelines/auto_pipeline.py
optimum/habana/diffusers/pipelines/pipeline_utils.py
optimum/habana/diffusers/pipelines/cogvideox/pipeline_cogvideox.py
optimum/habana/diffusers/pipelines/cogvideox/pipeline_cogvideox_image2video.py
optimum/habana/diffusers/pipelines/controlnet/pipeline_controlnet.py
optimum/habana/diffusers/pipelines/controlnet/pipeline_stable_video_diffusion_controlnet.py
optimum/habana/diffusers/pipelines/ddpm/pipeline_ddpm.py
optimum/habana/diffusers/pipelines/flux/pipeline_flux.py
optimum/habana/diffusers/pipelines/flux/pipeline_flux_img2img.py
optimum/habana/diffusers/pipelines/i2vgen_xl/pipeline_i2vgen_xl.py
optimum/habana/diffusers/pipelines/stable_diffusion/pipeline_stable_diffusion.py
optimum/habana/diffusers/pipelines/stable_diffusion/pipeline_stable_diffusion_depth2img.py
optimum/habana/diffusers/pipelines/stable_diffusion/pipeline_stable_diffusion_image_variation.py
optimum/habana/diffusers/pipelines/stable_diffusion/pipeline_stable_diffusion_img2img.py
optimum_habana-1.20.0.dist-info/licenses/LICENSE
optimum_habana-1.20.0.dist-info/METADATA
optimum_habana-1.20.0.dist-info/WHEEL
optimum_habana-1.20.0.dist-info/top_level.txt
optimum_habana-1.20.0.dist-info/RECORD
