Metadata-Version: 2.4
Name: optimum-habana
Version: 1.20.0
Summary: Optimum Habana is the interface between the Hugging Face Transformers and Diffusers libraries and Habana's Gaudi processor (HPU). It provides a set of tools enabling easy model loading, training and inference on single- and multi-HPU settings for different downstream tasks.
Home-page: https://huggingface.co/hardware/habana
Author: HuggingFace Inc. Special Ops Team
Author-email: hardware@huggingface.co
License: Apache
Keywords: transformers,diffusers,mixed-precision training,fine-tuning,gaudi,hpu
Classifier: Development Status :: 5 - Production/Stable
Classifier: License :: OSI Approved :: Apache Software License
Classifier: Intended Audience :: Developers
Classifier: Intended Audience :: Education
Classifier: Intended Audience :: Science/Research
Classifier: Operating System :: OS Independent
Classifier: Programming Language :: Python :: 3.8
Classifier: Programming Language :: Python :: 3.9
Classifier: Topic :: Scientific/Engineering :: Artificial Intelligence
License-File: LICENSE
Requires-Dist: transformers<4.56.0,>=4.55.0
Requires-Dist: optimum<2.1.0,>=2.0.0
Requires-Dist: torch
Requires-Dist: accelerate<=1.10.1,>=1.7.0
Requires-Dist: diffusers<0.34.1,>=0.34.0
Requires-Dist: huggingface_hub[hf_xet]>=0.24.7
Requires-Dist: sentence-transformers==3.3.1
Requires-Dist: sentencepiece
Provides-Extra: tests
Requires-Dist: psutil; extra == "tests"
Requires-Dist: parameterized; extra == "tests"
Requires-Dist: GitPython; extra == "tests"
Requires-Dist: optuna; extra == "tests"
Requires-Dist: sentencepiece; extra == "tests"
Requires-Dist: datasets==3.6.0; extra == "tests"
Requires-Dist: timm; extra == "tests"
Requires-Dist: safetensors; extra == "tests"
Requires-Dist: pytest<8.0.0; extra == "tests"
Requires-Dist: scipy; extra == "tests"
Requires-Dist: torchsde; extra == "tests"
Requires-Dist: timm; extra == "tests"
Requires-Dist: peft; extra == "tests"
Requires-Dist: bitsandbytes; extra == "tests"
Requires-Dist: tiktoken; extra == "tests"
Requires-Dist: blobfile; extra == "tests"
Provides-Extra: quality
Requires-Dist: ruff; extra == "quality"
Requires-Dist: hf_doc_builder; extra == "quality"
Dynamic: author
Dynamic: author-email
Dynamic: classifier
Dynamic: description
Dynamic: description-content-type
Dynamic: home-page
Dynamic: keywords
Dynamic: license
Dynamic: license-file
Dynamic: provides-extra
Dynamic: requires-dist
Dynamic: summary
